prometheus_push_client/__init__.py
prometheus_push_client/compat.py
prometheus_push_client/decorators.py
prometheus_push_client/metrics.py
prometheus_push_client/registry.py
prometheus_push_client/version.py
prometheus_push_client/clients/__init__.py
prometheus_push_client/clients/base.py
prometheus_push_client/clients/batch.py
prometheus_push_client/clients/streaming.py
prometheus_push_client/formats/__init__.py
prometheus_push_client/formats/base.py
prometheus_push_client/formats/influx.py
prometheus_push_client/formats/openmetrics.py
prometheus_push_client/formats/statsd.py
prometheus_push_client/transports/__init__.py
prometheus_push_client/transports/base.py
prometheus_push_client/transports/http.py
prometheus_push_client/transports/udp.py
prometheus_push_client-0.0.8.dist-info/LICENSE
prometheus_push_client-0.0.8.dist-info/METADATA
prometheus_push_client-0.0.8.dist-info/WHEEL
prometheus_push_client-0.0.8.dist-info/top_level.txt
prometheus_push_client-0.0.8.dist-info/RECORD
