Metadata-Version: 2.1
Name: prometheus-push-client
Version: 0.0.8
Summary: Push Prometheus metrics to VictoriaMetrics or other exporters
Home-page: https://github.com/gistart/prometheus-push-client
Author: gistart
Author-email: gistart@yandex.ru
License: Apache License 2.0
Platform: UNKNOWN
Classifier: Programming Language :: Python :: 3
Classifier: Programming Language :: Python :: 3.6
Classifier: Programming Language :: Python :: 3.7
Classifier: Programming Language :: Python :: 3.8
Classifier: Programming Language :: Python :: 3.9
Classifier: License :: OSI Approved :: Apache Software License
Classifier: Operating System :: OS Independent
Requires-Python: >=3.6
Requires-Dist: prometheus-client (>=0.4.0)
Provides-Extra: dev
Requires-Dist: aiohttp (<4) ; extra == 'dev'
Requires-Dist: ipython ; extra == 'dev'
Requires-Dist: pytest ; extra == 'dev'
Requires-Dist: pytest-asyncio ; extra == 'dev'
Requires-Dist: pytest-cov ; extra == 'dev'
Requires-Dist: pytest-mock ; extra == 'dev'
Requires-Dist: requests (<3) ; extra == 'dev'
Requires-Dist: setuptools ; extra == 'dev'
Requires-Dist: twine ; extra == 'dev'
Requires-Dist: wheel ; extra == 'dev'
Provides-Extra: http
Requires-Dist: aiohttp (<4) ; extra == 'http'
Requires-Dist: requests (<3) ; extra == 'http'
Provides-Extra: test
Requires-Dist: aiohttp (<4) ; extra == 'test'
Requires-Dist: pytest ; extra == 'test'
Requires-Dist: pytest-asyncio ; extra == 'test'
Requires-Dist: pytest-cov ; extra == 'test'
Requires-Dist: pytest-mock ; extra == 'test'
Requires-Dist: requests (<3) ; extra == 'test'
